{"1":"2009年 西班牙奔牛节拉开序幕",
"2":"1995年 法国超级间谍卫星出山",
"3":"1995年 长江下游出现建国后第二大洪水",
"4":"1994年 天文学家新发现太阳系外有行星",
"5":"1982年 电影艺术家金山逝世",
"6":"1981年 国务院下达鼓励个体经营的规定",
"7":"1981年 太阳能飞机首次飞越英吉利海峡",
"8":"1976年 皮定均中将逝世",
"9":"1974年 西德队获第十届世界杯足球赛冠军",
"10":"1972年 田中角荣当选为日本首相，中日关系实现正常化",
"11":"1968年 涉嫌暗杀肯尼迪之人被拘留",
"12":"1967年 英国影星费雯丽去世",
"13":"1950年 美国操纵联合国安理会通过非法决议 组织“联合国军司令部”",
"14":"1945年 中共中央纪念抗战八周年",
"15":"1945年 国民政府宣布对日军全面反攻",
"16":"1941年 美军接管冰岛",
"17":"1937年 卢沟桥事变",
"18":"1933年 多伦战斗正式打响",
"19":"1930年 英国作家柯南道尔去世",
"20":"1929年 美国东西海岸间的班机首次通航",
"21":"1928年 南京国民政府宣告废除中外不平等条约",
"22":"1927年 上海设立“特别市”",
"23":"1927年 冯玉祥礼送共产党出境",
"24":"1921年 中国劳动组合书记部成立",
"25":"1906年 周学熙创办启新洋灰公司",
"26":"1902年 清政府就英印军队进犯西藏照会英国",
"27":"1887年 俄国画家夏加尔诞辰",
"28":"1839年 林维喜事件",
"29":"1807年 法俄代表签署《提尔西特和约》",
"30":"1746年 意大利天文学家朱塞普·皮亚齐出生",
"31":"1307年 英国金雀花王朝第五任国王爱德华一世逝世",
"32":"23年 昆阳之战"}