{"1":"2010年 甘肃舟曲县发生特大泥石流",
"2":"2010年 圣元奶粉遭遇“女婴性早熟门”",
"3":"2009年 台风“莫拉克”重创台湾",
"4":"2009年 全国第一个“全民健身日”",
"5":"2008年 第29届北京奥运会开幕",
"6":"2008年 俄罗斯装甲部队进入南奥塞梯",
"7":"2007年 第24届世界大学生运动会开幕",
"8":"2002年 陈俊生逝世",
"9":"2001年 美国摧毁最大儿童色情网站",
"10":"2001年 第二十九届奥林匹克运动会组织委员会筹备办公室在京成立",
"11":"1999年 刘国梁在第45届世乒赛男单决赛中勇夺冠军",
"12":"1999年 我国首次使用自主研制的“实践五号”卫星圆满完成任务",
"13":"1998年 旅美华人抗议迫害印尼华人暴行",
"14":"1995年 京津塘高速公路验收后正式通车",
"15":"1994年 布达拉宫维修工程竣工",
"16":"1992年 中国第一个外汇调剂中心公开市场在北京正式开业",
"17":"1991年 美国人质约翰·麦卡锡获释",
"18":"1990年 我国与印度尼西亚恢复外交关系",
"19":"1987年 中国消化病学的奠基人张孝骞逝世",
"20":"1981年 黄植诚驾机起义回归祖国大陆",
"21":"1977年 邓小平在科学和教育工作座谈会上讲话",
"22":"1974年 尼克松因水门事件辞职",
"23":"1973年 金大中被绑架事件发生",
"24":"1968年 日本心脏移植手术引起震惊",
"25":"1967年 东南亚国家联盟成立",
"26":"1966年 八届十一中全会通过“文革”十六条",
"27":"1961年 梅兰芳病逝",
"28":"1952年 我国实行民族区域自治",
"29":"1946年 中共土改政策向富农让步",
"30":"1945年 苏联对日本宣战",
"31":"1944年 日军攻陷衡阳，在衡阳烧杀淫掠",
"32":"1940年 法国四名著名人物被维希政府逮捕",
"33":"1937年 达斯汀·霍夫曼出生",
"34":"1934年 营口坠龙事件",
"35":"1925年 美国4万名三K党党徒举行示威",
"36":"1918年 亚眠战役爆发",
"37":"1913年 讨袁军与北军在南京血战",
"38":"1902年 英国物理学家保罗·狄拉克诞生",
"39":"1901年 美国物理学家托马斯·劳伦斯诞生",
"40":"1891年 二战日本战犯土肥原贤二出生",
"41":"1866年 中国金石学家罗振玉出生",
"42":"1858年 英国击败西班牙无敌舰队",
"43":"1802年 俄国化学家盖斯出生",
"44":"公元前685年 齐鲁乾时之战，齐桓公的地位得到巩固"}