{"1":"2008年 柬埔寨和泰国军队在两国边境地区发生交火",
"2":"2007年 中国共产党第十七次全国代表大会在北京召开",
"3":"1998年 天安门广场万人表演太极拳",
"4":"1997年 华裔学者朱棣文获诺贝尔物理学奖",
"5":"1994年 海地流亡总统阿里斯蒂德重新执政",
"6":"1993年 曼德拉、德克勒克同获诺贝尔和平奖",
"7":"1993年 南非判处暗杀哈尼主犯刘易斯死刑",
"8":"1993年 世界最长光缆纵贯神州",
"9":"1991年 美国黑人大法官任命案风波结束",
"10":"1990年 现代诗人、红学家俞平伯在北京病逝",
"11":"1986年 美籍华人李远哲获诺贝尔化学奖",
"12":"1985年 北大西洋大会有条件地认可美“星球大战”计划",
"13":"1984年 旅美作家江南被刺",
"14":"1970年 我国与赤道几内亚建立外交关系",
"15":"1964年 哈罗德·威尔逊任英国首相",
"16":"1963年 路德维格·艾哈德当选西德首相",
"17":"1961年 周恩来参加苏共22大，阐明共产党立场",
"18":"1957年 中央制定“右派”分子的划分标准",
"19":"1957年 武汉长江大桥通车",
"20":"1948年 解放军攻克锦州",
"21":"1947年 世界第一次超音速飞机——喷气式飞机试飞",
"22":"1946年 纳粹德国空军部长戈林自杀",
"23":"1945年 法国民族叛徒赖伐尔被处决",
"24":"1944年 中国军队歼灭缅甸八莫、卡的克日军",
"25":"1929年 陈独秀取消主义的破产",
"26":"1925年 陈赓救蒋介石一命",
"27":"1925年 浙奉大战爆发",
"28":"1924年 美国汽车大王艾科卡诞辰",
"29":"1924年 广州商团叛乱被扑灭",
"30":"1917年 北京大学开始实行选科制",
"31":"1917年 荷兰双重间谍玛塔·哈莉被法军枪毙",
"32":"1915年 以色列“死脑筋”总理沙米尔诞辰",
"33":"1844年 德国哲学家尼采诞辰",
"34":"1814年 俄国诗人莱蒙托夫诞辰"}