{"1":"2014年 WHO发布全球空气最差20城市",
"2":"2011年 中国首台国产千万亿次计算机系统启用",
"3":"2009年 抗战摄影师徐肖冰去世",
"4":"2005年 法国发生严重骚乱",
"5":"2002年 “中国资源二号”卫星成功发射",
"6":"1999年 亚美尼亚总理瓦兹根·萨尔基相等遇刺身亡",
"7":"1999年 谢非在广州逝世",
"8":"1997年 我国签署《经济、社会及文化权利国际公约》",
"9":"1997年 首届世界中西医结合大会在京开幕",
"10":"1997年 50年前好莱坞“黑名单”平反",
"11":"1995年 卢泰愚承认自己执政期间非法侵占5000亿",
"12":"1995年 意前总理等政要被判刑",
"13":"1992年 百年巨鲟首次被捕获",
"14":"1991年 《保卫延安》的作者杜鹏程逝世",
"15":"1989年 苏销毁完全部中短程导弹",
"16":"1989年 英国发生政坛风波",
"17":"1989年 美宾夕法尼亚州发生监狱暴乱",
"18":"1988年 拉美八国集团首脑会议通过《乌拉圭宣言》",
"19":"1950年 任弼时逝世",
"20":"1947年 克什米尔战争爆发",
"21":"1947年 中共中央指示 将革命进行到底",
"22":"1940年 延安筹建新华广播电台",
"23":"1940年 卓别林的《大独裁者》上映",
"24":"1938年 日军对中国军队进行毒气战",
"25":"1937年 八百壮士坚守四行仓库",
"26":"1937年 伪“蒙古联盟自治政府”成立",
"27":"1927年 中共创建井冈山根据地",
"28":"1921年 思想家严复逝世",
"29":"1915年 美军进入一战前线",
"30":"1858年 美国总统西奥多·罗斯福诞辰",
"31":"1782年 意大利音乐家帕格尼尼诞辰",
"32":"1605年 印度莫卧儿王朝皇帝阿克巴大帝逝世",
"33":"1505年 俄中央集权国家奠基者——伊凡三世病逝",
"34":"公元前628年 春秋五霸之一晋文公重耳卒"}