{"1":"2014年 马云成为亚洲首富",
"2":"2005年 国内首次漆画拍卖会在厦门举行",
"3":"2002年 著名京剧表演艺术家袁世海辞世",
"4":"2002年 世界最大野生动物保护区建立",
"5":"2001年 我国正式加入世界贸易组织",
"6":"1997年 华盛顿联邦地方法院处罚微软公司",
"7":"1996年 超级计算机问世",
"8":"1996年 董建华当选香港特区第一任行政长官",
"9":"1995年 柏林发生一起信件爆炸事件",
"10":"1995年 女作家杨沫逝世",
"11":"1994年 俄罗斯决定解除车臣非法武装",
"12":"1994年 中科院首次获企业捐资",
"13":"1981年 考古学家发现世界上最古老的神庙",
"14":"1981年 中国首次举办托福考试",
"15":"1980年 中国颁发第一个工商个体户营业执照",
"16":"1964年 美国在南越开始进行“特种战争”",
"17":"1961年 唐代长安城遗址被发掘出来",
"18":"1948年 平津战役基本解放了华北地区",
"19":"1947年 开明绅士李鼎铭逝世",
"20":"1937年 南京保卫战激烈进行中，蒋介石决定令守军全部撤退",
"21":"1936年 英国国王爱德华八世宣布退位",
"22":"1936年 凯恩斯发表《就业、利息和货币通论》",
"23":"1931年 英国通过威斯敏斯特法案",
"24":"1929年 百色起义",
"25":"1927年 广州起义爆发",
"26":"1918年 俄罗斯作家索尔仁尼琴诞辰",
"27":"1915年 袁世凯称帝",
"28":"1914年 日本内阁通过对华“二十一条”",
"29":"1911年 “中国航天之父”钱学森诞辰",
"30":"1905年 清廷五大臣启程出洋考察",
"31":"1903年 殷墟甲骨开始流失国外",
"32":"1901年 中国劳工运动领导人陈郁诞生",
"33":"1876年 波兰作曲家米奇斯拉夫·卡洛维茨出生",
"34":"1863年 美国女天文学家、恒星光谱先驱者之一安妮·坎农诞生",
"35":"1843年 世界病原细菌学的奠基人罗伯特·科赫出生",
"36":"1803年 法国音乐家柏辽兹诞辰",
"37":"1754年 清代《儒林外史》作者吴敬梓逝世",
"38":"1572年 丹麦天文学者第谷发现了仙台星座中的一颗新星",
"39":"1515年 教皇利奥十世根据波洛尼亚条约把帕尔马等地割让给法国",
"40":"316年 西晋灭亡"}